backends/__init__.py
backends/cache_backend.py
backends/omnistone_backend.py
django_cassiopeia/__init__.py
django_cassiopeia/admin.py
django_cassiopeia/apps.py
django_cassiopeia/models.py
django_cassiopeia/tests.py
django_cassiopeia/utils.py
django_cassiopeia/views.py
stores/__init__.py
stores/django_cache.py
stores/omnistone.py
django_cassiopeia-2.1.1.dist-info/LICENSE.txt
django_cassiopeia-2.1.1.dist-info/METADATA
django_cassiopeia-2.1.1.dist-info/WHEEL
django_cassiopeia-2.1.1.dist-info/top_level.txt
django_cassiopeia-2.1.1.dist-info/zip-safe
django_cassiopeia-2.1.1.dist-info/RECORD
