Metadata-Version: 2.1
Name: django-cassiopeia
Version: 2.1.1
Summary: Django Integration of the Riot Games Developer API Wrapper 'cassiopeia'
Home-page: https://github.com/paaksing/django-cassiopeia
Author: Paaksing
Author-email: paaksingtech@gmail.com
License: MIT
Keywords: Django,LoL,League of Legends,Riot Games,API,REST
Platform: UNKNOWN
Classifier: Development Status :: 4 - Beta
Classifier: Programming Language :: Python :: 3.6
Classifier: Environment :: Web Environment
Classifier: Operating System :: OS Independent
Classifier: Intended Audience :: Developers
Classifier: License :: OSI Approved :: MIT License
Classifier: Topic :: Games/Entertainment
Classifier: Topic :: Games/Entertainment :: Real Time Strategy
Classifier: Topic :: Games/Entertainment :: Role-Playing
Classifier: Topic :: Software Development :: Libraries :: Python Modules
Classifier: Natural Language :: English
Classifier: Framework :: Django :: 3.0
Requires-Dist: datapipelines (>=1.0.7)
Requires-Dist: merakicommons (>=1.0.7)
Requires-Dist: cassiopeia
Requires-Dist: Pillow
Requires-Dist: arrow
Requires-Dist: requests
Requires-Dist: Django (>=3.0.1)
Requires-Dist: wheel
